README.md
setup.py
Nemotron/__init__.py
Nemotron/core.py
Nemotron.egg-info/PKG-INFO
Nemotron.egg-info/SOURCES.txt
Nemotron.egg-info/dependency_links.txt
Nemotron.egg-info/requires.txt
Nemotron.egg-info/top_level.txt