Metadata-Version: 2.2
Name: Nemotron
Version: 0.1.0
Summary: A wrapper for NEMOTRON chat API, Accountless!
Home-page: https://github.com/Ramona-Flower/Nemotron4free
Author: Ramona-Flower
Classifier: Programming Language :: Python :: 3
Classifier: License :: OSI Approved :: Apache Software License
Classifier: Operating System :: OS Independent
Requires-Dist: requests
Dynamic: author
Dynamic: classifier
Dynamic: description
Dynamic: description-content-type
Dynamic: home-page
Dynamic: requires-dist
Dynamic: summary
